dirdotenv/__init__.py
dirdotenv/__main__.py
dirdotenv/__version__.py
dirdotenv/cli.py
dirdotenv/loader.py
dirdotenv/parser.py
dirdotenv/hooks/__init__.py
dirdotenv/hooks/bash.sh
dirdotenv/hooks/fish.fish
dirdotenv/hooks/powershell.ps1
dirdotenv/hooks/zsh.sh
dirdotenv-0.0.3.dist-info/METADATA
dirdotenv-0.0.3.dist-info/WHEEL
dirdotenv-0.0.3.dist-info/entry_points.txt
dirdotenv-0.0.3.dist-info/RECORD
