Metadata-Version: 2.4
Name: dirdotenv
Version: 0.0.3
Summary: Like direnv, but works with both .envrc and .env files
Project-URL: Homepage, https://github.com/alexeygrigorev/dirdotenv
Project-URL: Repository, https://github.com/alexeygrigorev/dirdotenv
Author: Alexey Grigorev
Keywords: direnv,dotenv,env,environment,envrc,variables
Classifier: Development Status :: 3 - Alpha
Classifier: Intended Audience :: Developers
Classifier: Programming Language :: Python :: 3
Classifier: Programming Language :: Python :: 3.7
Classifier: Programming Language :: Python :: 3.8
Classifier: Programming Language :: Python :: 3.9
Classifier: Programming Language :: Python :: 3.10
Classifier: Programming Language :: Python :: 3.11
Classifier: Programming Language :: Python :: 3.12
Classifier: Topic :: Software Development :: Build Tools
Requires-Python: >=3.7
